solverforge-0.2.6.dist-info/METADATA
solverforge-0.2.6.dist-info/WHEEL
solverforge/__init__.py
solverforge/_solverforge.pypy311-pp73-x86_64-linux-gnu.so
solverforge/solver/__init__.py
solverforge/solver/config.py
solverforge/solver/domain.py
solverforge/solver/score.py
solverforge/test/__init__.py
solverforge-0.2.6.dist-info/RECORD
