Metadata-Version: 2.4
Name: solverforge
Version: 0.2.6
Classifier: Programming Language :: Rust
Classifier: Programming Language :: Python :: Implementation :: CPython
Classifier: Programming Language :: Python :: 3
Classifier: Programming Language :: Python :: 3.10
Classifier: Programming Language :: Python :: 3.11
Classifier: Programming Language :: Python :: 3.12
Classifier: Programming Language :: Python :: 3.13
Classifier: Development Status :: 3 - Alpha
Classifier: Intended Audience :: Developers
Classifier: License :: OSI Approved :: Apache Software License
Classifier: Topic :: Scientific/Engineering :: Artificial Intelligence
Summary: Python bindings for SolverForge constraint solver
Keywords: constraint,solver,optimization,scheduling,planning
License: Apache-2.0
Requires-Python: >=3.10
Project-URL: Homepage, https://solverforge.org
Project-URL: Documentation, https://docs.solverforge.org
Project-URL: Repository, https://github.com/solverforge/solverforge
Project-URL: Bug Tracker, https://github.com/solverforge/solverforge/issues
Project-URL: Changelog, https://github.com/solverforge/solverforge/blob/main/CHANGELOG.md
